AUTHORS.txt
COPYING.txt
HISTORY.txt
MANIFEST.in
README.txt
ez_setup.py
setup.py
RESTinpy/__init__.py
RESTinpy/adapters.py
RESTinpy/auth.py
RESTinpy/decorators.py
RESTinpy/formatters.py
RESTinpy/model_resources.py
RESTinpy/resources.py
RESTinpy/utils.py
RESTinpy.egg-info/PKG-INFO
RESTinpy.egg-info/SOURCES.txt
RESTinpy.egg-info/dependency_links.txt
RESTinpy.egg-info/requires.txt
RESTinpy.egg-info/top_level.txt